{
	"label": "Foreign Policy",
	"description": "A selection of titles on foreign policy available from the European Parliament Library.",
	"list": [{
			"label": "Crisis and Change in European Union Foreign Policy",
			"isbns": [
				"9781526182586"
			]
		},
		{
			"label": "Norm Contestation in EU Foreign Policy",
			"isbns": [
				"9783031851520"
			]
		},
		{
			"label": "The EU's Strategic Dilemma in the Ukraine War",
			"isbns": [
				"9783032015952"
			]
		},
		{
			"label": "Security in 21st Century Europe",
			"isbns": [
				"9781137006455"
			]
		},
		{
			"label": "EU Foreign Policy in a Fragmenting International Order",
			"isbns": [
				"9783031640605"
			]
		},
		{
			"label": "A Geopolitical Europe in the Making?",
			"isbns": [
				"9789462656666"
			]
		},
		{
			"label": "Europe in an Era of US-China Strategic Rivalry",
			"isbns": [
				"9783031481178"
			]
		}
		
	]
}
