{
	"label": "Books on Sustainable Tourism",
	"description": "A selection of titles on sustainable tourism available from the European Parliament Library.",
	"list": [{
			"label": "Sustainable Tourism, Culture and Heritage Promotion : Development, Management and Connectivity",
			"isbns": [
				"9783031495366"
			]
		},
		{
			"label": "Event Tourism and Sustainable Community Development : Advances, Effects, and Implications",
			"isbns": [
				"9781000772050"
			]
		},
		{
			"label": "Environment, Resources and Sustainable Tourism, Goa as a Case Study",
			"isbns": [
				"9789819918430"
			]
		},
		{
			"label": "Cultural sustainable tourism, strategic planning for a sustainable development",
			"isbns": [
				"9783031108006"
			]
		},
		{
			"label": "Routledge Handbook of Sustainable Heritage",
			"isbns": [
				"9781003038955"
			]
		}
	]
}
